README.md
setup.py
bifrost_py/__init__.py
bifrost_py/bifrost_py.py
bifrost_py/local_settings.py
bifrost_py/requirements.txt
bifrost_py/sample.py
bifrost_py/test.py
bifrost_py.egg-info/PKG-INFO
bifrost_py.egg-info/SOURCES.txt
bifrost_py.egg-info/dependency_links.txt
bifrost_py.egg-info/top_level.txt
bifrost_py/abi/Bifrost.json
bifrost_py/abi/BifrostProxy.json
bifrost_py/abi/IERC20.json