Metadata-Version: 2.1
Name: bifrost-py
Version: 0.0.5
Summary: Wallets based on SALT instead of Nonce.
Home-page: https://gitlab.riaquest.com/nacho/bifrost
Author: Ignacio Althabe
Author-email: nacho.althabe@gmail.com 
License: UNKNOWN
Platform: UNKNOWN
Classifier: Programming Language :: Python :: 3
Classifier: License :: OSI Approved :: MIT License
Classifier: Operating System :: OS Independent
